number_adder/__init__.py
number_adder/cli.py
number_adder/database.py
number_adder/server.py
number_adder/static/cancel.html
number_adder/static/dashboard.html
number_adder/static/index.html
number_adder/static/pricing.html
number_adder/static/privacy.html
number_adder/static/settings.html
number_adder/static/success.html
number_adder-0.3.0.dist-info/METADATA
number_adder-0.3.0.dist-info/WHEEL
number_adder-0.3.0.dist-info/entry_points.txt
number_adder-0.3.0.dist-info/top_level.txt
number_adder-0.3.0.dist-info/RECORD
