Metadata-Version: 2.4
Name: number-adder
Version: 0.3.0
Summary: A simple number adding service with GDPR compliance
Author-email: Your Name <you@example.com>
License-Expression: MIT
Requires-Python: >=3.8
Requires-Dist: fastapi>=0.104.0
Requires-Dist: uvicorn>=0.24.0
Requires-Dist: bcrypt>=4.0.0
Requires-Dist: python-jose[cryptography]>=3.3.0
Requires-Dist: pydantic[email]>=2.0.0
Requires-Dist: stripe>=7.0.0
Requires-Dist: httpx>=0.25.0
